{
    "symbol": "A",
    "name": "Archbishop",
    "IsDivergent": false,
    "CheckDuplicateMoves": false,
    "EstimatedValue": 8.7,
    "slidemovevectors": [
        {
            "x": 1,
            "y": 1,
            "maxrange": 0
        },
        {
            "x": 1,
            "y": -1,
            "maxrange": 0
        },
        {
            "x": -1,
            "y": -1,
            "maxrange": 0
        },
        {
            "x": -1,
            "y": 1,
            "maxrange": 0
        },
        {
            "x": 1,
            "y": 2,
            "maxrange": 1
        },
        {
            "x": 2,
            "y": 1,
            "maxrange": 1
        },
        {
            "x": 2,
            "y": -1,
            "maxrange": 1
        },
        {
            "x": 1,
            "y": -2,
            "maxrange": 1
        },
        {
            "x": -1,
            "y": -2,
            "maxrange": 1
        },
        {
            "x": -2,
            "y": -1,
            "maxrange": 1
        },
        {
            "x": -2,
            "y": 1,
            "maxrange": 1
        },
        {
            "x": -1,
            "y": 2,
            "maxrange": 1
        }
    ]
}